.gitignore
.gitmodules
CHANGES.txt
MANIFEST.in
README.rst
development.ini
gulpfile.js
i18n.sh
package-lock.json
package.json
pip-selfcheck.json
pytest.ini
setup.cfg
setup.py
kotti_tinymce/__init__.py
kotti_tinymce.egg-info/PKG-INFO
kotti_tinymce.egg-info/SOURCES.txt
kotti_tinymce.egg-info/dependency_links.txt
kotti_tinymce.egg-info/entry_points.txt
kotti_tinymce.egg-info/not-zip-safe
kotti_tinymce.egg-info/requires.txt
kotti_tinymce.egg-info/top_level.txt
kotti_tinymce/locale/kotti_tinymce.pot
kotti_tinymce/locale/cs/LC_MESSAGES/kotti_tinymce.mo
kotti_tinymce/locale/cs/LC_MESSAGES/kotti_tinymce.po
kotti_tinymce/locale/da/LC_MESSAGES/kotti_tinymce.mo
kotti_tinymce/locale/da/LC_MESSAGES/kotti_tinymce.po
kotti_tinymce/locale/de/LC_MESSAGES/kotti_tinymce.mo
kotti_tinymce/locale/de/LC_MESSAGES/kotti_tinymce.po
kotti_tinymce/locale/de_DE/LC_MESSAGES/kotti_tinymce.mo
kotti_tinymce/locale/de_DE/LC_MESSAGES/kotti_tinymce.po
kotti_tinymce/locale/es/LC_MESSAGES/kotti_tinymce.mo
kotti_tinymce/locale/es/LC_MESSAGES/kotti_tinymce.po
kotti_tinymce/locale/fr/LC_MESSAGES/kotti_tinymce.mo
kotti_tinymce/locale/fr/LC_MESSAGES/kotti_tinymce.po
kotti_tinymce/locale/fr_FR/LC_MESSAGES/kotti_tinymce.mo
kotti_tinymce/locale/fr_FR/LC_MESSAGES/kotti_tinymce.po
kotti_tinymce/locale/it/LC_MESSAGES/kotti_tinymce.mo
kotti_tinymce/locale/it/LC_MESSAGES/kotti_tinymce.po
kotti_tinymce/locale/ja/LC_MESSAGES/kotti_tinymce.mo
kotti_tinymce/locale/ja/LC_MESSAGES/kotti_tinymce.po
kotti_tinymce/locale/ko/LC_MESSAGES/kotti_tinymce.mo
kotti_tinymce/locale/ko/LC_MESSAGES/kotti_tinymce.po
kotti_tinymce/locale/nl/LC_MESSAGES/kotti_tinymce.mo
kotti_tinymce/locale/nl/LC_MESSAGES/kotti_tinymce.po
kotti_tinymce/locale/pl/LC_MESSAGES/kotti_tinymce.mo
kotti_tinymce/locale/pl/LC_MESSAGES/kotti_tinymce.po
kotti_tinymce/locale/pt/LC_MESSAGES/kotti_tinymce.mo
kotti_tinymce/locale/pt/LC_MESSAGES/kotti_tinymce.po
kotti_tinymce/locale/pt_BR/LC_MESSAGES/kotti_tinymce.mo
kotti_tinymce/locale/pt_BR/LC_MESSAGES/kotti_tinymce.po
kotti_tinymce/locale/ru/LC_MESSAGES/kotti_tinymce.mo
kotti_tinymce/locale/ru/LC_MESSAGES/kotti_tinymce.po
kotti_tinymce/locale/sv/LC_MESSAGES/kotti_tinymce.mo
kotti_tinymce/locale/sv/LC_MESSAGES/kotti_tinymce.po
kotti_tinymce/static/kotti_tinymce.js
