Metadata-Version: 2.1
Name: kotti-tinymce
Version: 0.7.1
Summary: TinyMCE plugins for Kotti
Home-page: https://github.com/Kotti/kotti_tinymce
Author: Andreas Kaiser
Author-email: disko@binary-punks.com
License: BSD
Keywords: tinymce image browser kotti cms pylons pyramid
Platform: UNKNOWN
Classifier: Programming Language :: Python
Classifier: Framework :: Pylons
Classifier: Topic :: Internet :: WWW/HTTP
Classifier: Topic :: Internet :: WWW/HTTP :: Dynamic Content
Classifier: Topic :: Internet :: WWW/HTTP :: WSGI :: Application
Classifier: License :: OSI Approved :: MIT License
Provides-Extra: development
Provides-Extra: testing
